rdv/__init__.py
rdv/feature.py
rdv/globals.py
rdv/schema.py
rdv/stats.py
rdv/tags.py
rdv/version.py
rdv/dash/__init__.py
rdv/dash/helpers.py
rdv/extractors/__init__.py
rdv/extractors/structured/__init__.py
rdv/extractors/structured/element.py
rdv/extractors/structured/kmeans.py
rdv/extractors/vision/__init__.py
rdv/extractors/vision/dn2.py
rdv/extractors/vision/intensity.py
rdv/extractors/vision/sharpness.py
rdv/extractors/vision/similarity.py
rdv/tests/__init__.py
rdv/tests/test_buildable.py
rdv/tests/test_check.py
rdv/tests/test_features.py
rdv/tests/test_serializable.py
rdv-0.0.9.dist-info/LICENSE.md
rdv-0.0.9.dist-info/METADATA
rdv-0.0.9.dist-info/WHEEL
rdv-0.0.9.dist-info/top_level.txt
rdv-0.0.9.dist-info/RECORD
