Metadata-Version: 2.1
Name: rdv
Version: 0.0.9
Summary: Raymon Data Validation Package.
Home-page: https://raymon.ai
Author: Raymon.ai
Author-email: hello@raymon.ai
License: MIT
Platform: UNKNOWN
Classifier: Programming Language :: Python :: 3
Requires-Python: >=3.6
Requires-Dist: pandas
Requires-Dist: selenium
Requires-Dist: dash
Requires-Dist: numpy
Requires-Dist: imagehash
Requires-Dist: plotly
Requires-Dist: torch
Requires-Dist: torchvision
Requires-Dist: jupyter-dash
Requires-Dist: sklearn
